geologs/__init__.py
geologs/__main__.py
geologs/basic.py
geologs/commands.py
geologs/geologs.py
geologs/parsers.py
geologs/watch_logs.py
geologs-1.0.dist-info/LICENSE.txt
geologs-1.0.dist-info/METADATA
geologs-1.0.dist-info/WHEEL
geologs-1.0.dist-info/entry_points.txt
geologs-1.0.dist-info/top_level.txt
geologs-1.0.dist-info/RECORD
