Metadata-Version: 2.1
Name: geologs
Version: 1.0
Summary: Slack bot to watch log files and run basic server commands
Author-email: gyndlf <james@zingel.co.nz>
License: MIT
Project-URL: repository, https://github.com/gyndlf/geologs
Keywords: slack,log,bot
License-File: LICENSE.txt
Requires-Dist: slack_bolt<=2.0
Requires-Dist: aiohttp<=4.0
